fig_cli/__init__.py
fig_cli/__main__.py
fig_cli/cli.py
fig_cli/utils.py
fig_cli/fig_project_template/.DS_Store
fig_cli/fig_project_template/cookiecutter.json
fig_cli/fig_project_template/hooks/post_gen_project.py
fig_cli/fig_project_template/{{cookiecutter.project_name}}/.DS_Store
fig_cli/fig_project_template/{{cookiecutter.project_name}}/.gitignore
fig_cli/fig_project_template/{{cookiecutter.project_name}}/CONTRIBUTING.md
fig_cli/fig_project_template/{{cookiecutter.project_name}}/README.md
fig_cli/fig_project_template/{{cookiecutter.project_name}}/app.py
fig_cli/fig_project_template/{{cookiecutter.project_name}}/requirements.txt
fig_cli/fig_project_template/{{cookiecutter.project_name}}/setup.py
fig_cli/fig_project_template/{{cookiecutter.project_name}}/bin/.keep
fig_cli/fig_project_template/{{cookiecutter.project_name}}/config/__init__.py
fig_cli/fig_project_template/{{cookiecutter.project_name}}/config/publish.toml
fig_cli/fig_project_template/{{cookiecutter.project_name}}/config/routes.py
fig_cli/fig_project_template/{{cookiecutter.project_name}}/config/secrets.toml
fig_cli/fig_project_template/{{cookiecutter.project_name}}/config/versions.toml
fig_cli/fig_project_template/{{cookiecutter.project_name}}/docs/.keep
fig_cli/fig_project_template/{{cookiecutter.project_name}}/public/.DS_Store
fig_cli/fig_project_template/{{cookiecutter.project_name}}/public/404.html
fig_cli/fig_project_template/{{cookiecutter.project_name}}/public/500.html
fig_cli/fig_project_template/{{cookiecutter.project_name}}/public/index.html
fig_cli/fig_project_template/{{cookiecutter.project_name}}/public/assets/.DS_Store
fig_cli/fig_project_template/{{cookiecutter.project_name}}/public/assets/css/fig.css
fig_cli/fig_project_template/{{cookiecutter.project_name}}/public/assets/imgs/fig.png
fig_cli/fig_project_template/{{cookiecutter.project_name}}/{{cookiecutter.project_name}}/__init__.py
fig_cli/fig_project_template/{{cookiecutter.project_name}}/{{cookiecutter.project_name}}/data_sources.py
FigCLI-0.1.1.dist-info/METADATA
FigCLI-0.1.1.dist-info/WHEEL
FigCLI-0.1.1.dist-info/entry_points.txt
FigCLI-0.1.1.dist-info/top_level.txt
FigCLI-0.1.1.dist-info/RECORD
