Metadata-Version: 2.1
Name: FigCLI
Version: 0.1.1
Summary: The batteries included, convention over configuration, python, data science, application framework
Home-page: UNKNOWN
Author: Fig Development Team
Author-email: figframework@gmail.com
License: MIT
Platform: UNKNOWN
Classifier: License :: OSI Approved :: MIT License
Classifier: Programming Language :: Python :: 3
Classifier: Programming Language :: Python :: 3.7
Requires-Dist: cookiecutter
Requires-Dist: click
Requires-Dist: PyInquirer
